transfer/__init__.py
transfer/__main__.py
transfer/cli.py
transfer/exceptions.py
transfer/request.py
transfer/table.py
transfer/version.py
transfer.sh-2.0.1.dist-info/LICENSE
transfer.sh-2.0.1.dist-info/METADATA
transfer.sh-2.0.1.dist-info/WHEEL
transfer.sh-2.0.1.dist-info/entry_points.txt
transfer.sh-2.0.1.dist-info/top_level.txt
transfer.sh-2.0.1.dist-info/RECORD
