Metadata-Version: 2.1
Name: transfer.sh
Version: 2.0.1
Summary: Transfer.sh command line program, Now file sharing from the command line.
Home-page: https://github.com/MayankFawkes/transfer.sh
Author: Mayank Gupta
Author-email: mayankfawkes@gmail.com
License: MIT License
Project-URL: Documentation, https://github.com/MayankFawkes/transfer.sh/blob/master/README.md
Project-URL: Source, https://github.com/MayankFawkes/transfer.sh
Keywords: upload,cli,transfer.sh
Platform: UNKNOWN
Classifier: Topic :: Software Development :: Libraries :: Python Modules
Classifier: Programming Language :: Python :: Implementation
Classifier: Programming Language :: Python :: 3 :: Only
Classifier: Programming Language :: Python :: 3
Classifier: Programming Language :: Python :: 3.6
Classifier: Programming Language :: Python :: 3.7
Classifier: Programming Language :: Python :: 3.8
Classifier: Programming Language :: Python :: 3.9
Classifier: License :: OSI Approved :: MIT License
Classifier: Development Status :: 5 - Production/Stable
Classifier: Topic :: System :: Networking
Classifier: Topic :: Internet :: WWW/HTTP
Classifier: Natural Language :: English
Classifier: Environment :: Plugins
Classifier: Environment :: Console
Classifier: Topic :: Terminals
Classifier: Topic :: Utilities
Requires-Python: >=3.6
Requires-Dist: requests
